mplatform/__init__.py
mplatform/handle.py
mplatform/roundtech.py
mplatform/tkui.py
mplatform-0.9.9.dist-info/LICENSE
mplatform-0.9.9.dist-info/METADATA
mplatform-0.9.9.dist-info/WHEEL
mplatform-0.9.9.dist-info/top_level.txt
mplatform-0.9.9.dist-info/RECORD
