Metadata-Version: 2.1
Name: mplatform
Version: 0.9.9
Summary: Quick code support
Home-page: UNKNOWN
Author: Minh Phuong BUI
Author-email: phuong.buiminh00@gmail.com
License: MIT
Platform: UNKNOWN
Classifier: Programming Language :: Python :: 3
Classifier: License :: OSI Approved :: MIT License
Classifier: Operating System :: OS Independent
